sickrage/__init__.py
sickrage/checksums.md5
sickrage/version.txt
sickrage/autoProcessTV/__init__.py
sickrage/autoProcessTV/autoProcessTV.cfg.sample
sickrage/autoProcessTV/autoProcessTV.py
sickrage/autoProcessTV/hellaToSiCKRAGE.py
sickrage/autoProcessTV/mediaToSiCKRAGE.py
sickrage/autoProcessTV/sabToSiCKRAGE.py
sickrage/clients/__init__.py
sickrage/clients/nzb/__init__.py
sickrage/clients/nzb/download_station.py
sickrage/clients/nzb/nzbget.py
sickrage/clients/nzb/sabnzbd.py
sickrage/clients/torrent/__init__.py
sickrage/clients/torrent/deluge.py
sickrage/clients/torrent/deluged.py
sickrage/clients/torrent/download_station.py
sickrage/clients/torrent/mlnet.py
sickrage/clients/torrent/putio.py
sickrage/clients/torrent/qbittorrent.py
sickrage/clients/torrent/rtorrent.py
sickrage/clients/torrent/transmission.py
sickrage/clients/torrent/utorrent.py
sickrage/core/__init__.py
sickrage/core/announcements.py
sickrage/core/auto_backup.py
sickrage/core/blackandwhitelist.py
sickrage/core/classes.py
sickrage/core/common.py
sickrage/core/enums.py
sickrage/core/google_drive.py
sickrage/core/imdb_popular.py
sickrage/core/nzbSplitter.py
sickrage/core/process_tv.py
sickrage/core/scene_numbering.py
sickrage/core/search.py
sickrage/core/traktapi.py
sickrage/core/ui.py
sickrage/core/upnp.py
sickrage/core/version_updater.py
sickrage/core/amqp/__init__.py
sickrage/core/amqp/consumer.py
sickrage/core/amqp/protos/announcement_v1_pb2.py
sickrage/core/amqp/protos/network_timezone_v1_pb2.py
sickrage/core/amqp/protos/search_provider_url_v1_pb2.py
sickrage/core/amqp/protos/server_certificate_v1_pb2.py
sickrage/core/amqp/protos/updates_v1_pb2.py
sickrage/core/api/__init__.py
sickrage/core/api/exceptions.py
sickrage/core/auth/__init__.py
sickrage/core/caches/__init__.py
sickrage/core/caches/image_cache.py
sickrage/core/caches/name_cache.py
sickrage/core/caches/tv_cache.py
sickrage/core/config/__init__.py
sickrage/core/config/helpers.py
sickrage/core/databases/__init__.py
sickrage-10.0.71.dist-info/COPYING.txt
sickrage-10.0.71.dist-info/METADATA
sickrage-10.0.71.dist-info/WHEEL
sickrage-10.0.71.dist-info/entry_points.txt
sickrage-10.0.71.dist-info/top_level.txt
sickrage-10.0.71.dist-info/RECORD
